[

    {
    "dica": "Item de esporte",
    "palavra": "raquete"
    },

    {
    "dica": "Fruta",
    "palavra": "banana"
    },

    {
    "dica": "Fruta",
    "palavra": "laranja"
    },
    
    {
    "dica": "Linguagem de progração de alto nivel",
    "palavra": "python"
    },
    
    {
    "dica": "Empresa famosa de tecnologia",
    "palavra": "apple"
    },

    {
    "dica": "Filme famoso de SuperHeroi",
    "palavra": "Thor"
    },

    {
    "dica": "Time famoso do Rio Grande Do Sul",
    "palavra": "Gremio"
    },

    {
    "dica": "Animal doméstico",
    "palavra": "Peixe"
    },
    
    {
    "dica": "Filme de Romance",
    "palavra": "After"
    },
    
    {
    "dica": " Um dos 50 Estados dos Estados Unidos",
    "palavra": "Missuri"
    }
]